pyjsparser/__init__.py
pyjsparser/parser.py
pyjsparser/pyjsparserdata.py
pyjsparser/std_nodes.py
pyjsparser_wheel-2.7.1.dist-info/LICENSE
pyjsparser_wheel-2.7.1.dist-info/METADATA
pyjsparser_wheel-2.7.1.dist-info/WHEEL
pyjsparser_wheel-2.7.1.dist-info/top_level.txt
pyjsparser_wheel-2.7.1.dist-info/RECORD
